JO_AutoMl/__init__.py
JO_AutoMl/all_hyperPara.py
JO_AutoMl/all_model_dic.py
JO_AutoMl/all_names.py
JO_AutoMl/all_require_paths.py
JO_AutoMl/classification.py
JO_AutoMl/classifierTrainer.py
JO_AutoMl/clusterANDtransformation.py
JO_AutoMl/combine_all.py
JO_AutoMl/detect_outlierANDremove.py
JO_AutoMl/diamensionalityReduction.py
JO_AutoMl/exception.py
JO_AutoMl/find_Corr_remove.py
JO_AutoMl/handle_categorical_features.py
JO_AutoMl/handle_imbalanced_dataset.py
JO_AutoMl/handle_missing_value_in_catData.py
JO_AutoMl/hyper_parameter.py
JO_AutoMl/model_score.py
JO_AutoMl/regression.py
JO_AutoMl/remove_unwntedColumns.py
JO_AutoMl/replace_NaN.py
JO_AutoMl/train_test_split.py
JO_AutoMl/transformation.py
JO_AutoMl_Sathishmahi-0.0.5.dist-info/LICENSE
JO_AutoMl_Sathishmahi-0.0.5.dist-info/METADATA
JO_AutoMl_Sathishmahi-0.0.5.dist-info/WHEEL
JO_AutoMl_Sathishmahi-0.0.5.dist-info/top_level.txt
JO_AutoMl_Sathishmahi-0.0.5.dist-info/RECORD
