Metadata-Version: 2.1
Name: JO-AutoMl-Sathishmahi
Version: 0.0.5
Summary: its a ML,in this library cover almost every ML process.this library mostly used for biginner
Home-page: https://github.com/Sathishmahi/JO_AutoMl
Author: Sathishmahi
Author-email: sathishmahi433@gmail.com
Project-URL: Bug Tracker, https://github.com/Sathishmahi/JO_AutoMl/issues
Classifier: Programming Language :: Python :: 3
Classifier: License :: OSI Approved :: MIT License
Classifier: Operating System :: OS Independent
Requires-Python: >=3.7
License-File: LICENSE
Requires-Dist: pandas
Requires-Dist: numpy
Requires-Dist: scikit-learn
Requires-Dist: joblib
Requires-Dist: matplotlib
Requires-Dist: seaborn
Requires-Dist: xgboost
Requires-Dist: imblearn
